strange/__init__.py
strange/learners/__init__.py
strange/learners/_ar.py
strange/learners/_black_box.py
strange/learners/_boosted.py
strange/learners/_predict_constant.py
strange/learners/_predict_last.py
strange/learners/core.py
strange/utils/__init__.py
strange/utils/random.py
strange/utils/statistics.py
strange/utils/validation.py
strange/utils/losses/__init__.py
strange/utils/losses/_cross_entropy.py
strange/utils/losses/_huber.py
strange/utils/losses/_mean_absolute_error.py
strange/utils/losses/_mean_bias_error.py
strange/utils/losses/_mean_square_error.py
strange/utils/losses/core.py
strange/utils/optimizers/__init__.py
strange/utils/optimizers/_ogd.py
strange/utils/optimizers/core.py
tests/__init__.py
tests/learners/__init__.py
tests/learners/test_ar.py
tests/learners/test_predict_constant.py
tests/learners/test_predict_last.py
strange-0.0.1.dist-info/LICENSE
strange-0.0.1.dist-info/METADATA
strange-0.0.1.dist-info/WHEEL
strange-0.0.1.dist-info/top_level.txt
strange-0.0.1.dist-info/RECORD
