Metadata-Version: 2.1
Name: strange
Version: 0.0.1
Summary: Online time series analysis
Home-page: https://github.com/MinRegret/strange
Author: Google AI Princeton
Author-email: dsuo@google.com
License: UNKNOWN
Keywords: timeseries,time,series,analysis
Platform: UNKNOWN
Classifier: Development Status :: 3 - Alpha
Classifier: Programming Language :: Python :: 3.5
Classifier: Programming Language :: Python :: 3.6
Classifier: Programming Language :: Python :: 3.7
Classifier: Programming Language :: Python :: 3.8
Classifier: License :: OSI Approved :: MIT License
Classifier: Operating System :: OS Independent
Requires-Python: >=3.5
Requires-Dist: numpy
Requires-Dist: scipy
Requires-Dist: cython
Requires-Dist: jax
Requires-Dist: jaxlib
Requires-Dist: scikit-learn
Requires-Dist: matplotlib
Provides-Extra: dev
Requires-Dist: flake8 ; extra == 'dev'
Requires-Dist: flake8-print ; extra == 'dev'
Requires-Dist: flake8-bugbear ; extra == 'dev'
Requires-Dist: mypy ; extra == 'dev'
Requires-Dist: pytest ; extra == 'dev'
Requires-Dist: pytest-xdist ; extra == 'dev'
Requires-Dist: pytest-cov ; extra == 'dev'
Requires-Dist: pylint ; extra == 'dev'
Requires-Dist: black ; extra == 'dev'
Requires-Dist: reorder-python-imports ; extra == 'dev'
Requires-Dist: autoflake ; extra == 'dev'
Requires-Dist: pre-commit ; extra == 'dev'
Requires-Dist: pydocstring-coverage ; extra == 'dev'
Requires-Dist: bumpversion ; extra == 'dev'
Requires-Dist: ipython ; extra == 'dev'
Requires-Dist: jupyter ; extra == 'dev'
Requires-Dist: pixiedust ; extra == 'dev'
Requires-Dist: ipdb ; extra == 'dev'
